django_bitmask_field.py
django_bitmask_field-0.1.3.dist-info/LICENSE
django_bitmask_field-0.1.3.dist-info/METADATA
django_bitmask_field-0.1.3.dist-info/WHEEL
django_bitmask_field-0.1.3.dist-info/top_level.txt
django_bitmask_field-0.1.3.dist-info/RECORD
